mongars/__init__.py
mongars/accounts.py
mongars/cli.py
mongars/display.py
mongars/gauth.py
mongars/imap.py
mongars/notifications.py
mongars/passwordstore.py
mongars-1.4.5.dist-info/METADATA
mongars-1.4.5.dist-info/WHEEL
mongars-1.4.5.dist-info/entry_points.txt
mongars-1.4.5.dist-info/licenses/LICENSE
mongars-1.4.5.dist-info/RECORD
