Metadata-Version: 2.3
Name: mongars
Version: 1.4.5
Summary: Show unread emails in INBOX using Gmail Api or Gnome Online Accounts
Author-email: Chmouel Boudjnah <chmouel@chmouel.com>
License: Apache-2.0
Classifier: License :: OSI Approved :: Apache Software License
Requires-Python: >=3.12
Requires-Dist: google-api-python-client>=2.153.0
Requires-Dist: google-auth-oauthlib>=1.2.1
Requires-Dist: google-auth>=2.36.0
Requires-Dist: pygobject>=3.50.0
